[
  {
    "id": "5ul4x12qkq",
    "status": "not-open",
    "company": "CMB Wing Lung Bank",
    "name": "Intern"
  },
  {
    "id": "5wkbia6x4o",
    "status": "not-open",
    "company": "Hilti Group",
    "name": "Summer Internship - Finance"
  },
  {
    "id": "6zv33ddm38",
    "status": "open",
    "company": "DRW",
    "name": "Quantitative Trading Analyst Intern"
  },
  {
    "id": "7bl7pbk19i",
    "status": "not-open",
    "company": "Smith",
    "name": "2027 Summer Intern - Credit"
  },
  {
    "id": "7svahowr87",
    "status": "open",
    "company": "Aqumon",
    "name": "Intern - Quantitative Researcher"
  },
  {
    "id": "8giqidjxg2",
    "status": "not-open",
    "company": "Man Group",
    "name": "Quantitative Research Intern - Specialist Equities"
  },
  {
    "id": "a29pqcbfq9",
    "status": "open",
    "company": "Bank of America",
    "name": "Summer 2027 Analyst Programme"
  },
  {
    "id": "aqusqao4yx",
    "status": "not-open",
    "company": "American Express",
    "name": "2027 Summer Internship"
  },
  {
    "id": "b87zlh1xx1",
    "status": "open",
    "company": "Citadel",
    "name": "Quantitative Research Analyst Intern"
  },
  {
    "id": "betppijr9h",
    "status": "open",
    "company": "Jefferies",
    "name": "2027 Summer Analyst Program"
  },
  {
    "id": "c506zq4vw0",
    "status": "not-open",
    "company": "The Bank of East Asia (BEA)",
    "name": "2027 Summer Internship"
  },
  {
    "id": "cdwvibszp8",
    "status": "not-open",
    "company": "NASDAQ",
    "name": "Market Research and Development Intern"
  },
  {
    "id": "cgo0nwcwp9",
    "status": "closed",
    "company": "Millennium Management",
    "name": "Millennium Investment Internship 2027"
  },
  {
    "id": "ckmc0mfbaw",
    "status": "not-open",
    "company": "Peak Re",
    "name": "2027 Internship Program"
  },
  {
    "id": "cmyrkv998l",
    "status": "open",
    "company": "Goldman Sachs",
    "name": "2027 Summer Analyst"
  },
  {
    "id": "czbar078zr",
    "status": "open",
    "company": "J.P. Morgan",
    "name": "2027 Summer Analyst"
  },
  {
    "id": "d901l41b9l",
    "status": "not-open",
    "company": "China Construction Bank (Asia)",
    "name": "[Programme Name TBC]"
  },
  {
    "id": "de382bk4yo",
    "status": "open",
    "company": "Point72",
    "name": "2027 Summer Internship"
  },
  {
    "id": "e1j7xkfh6h",
    "status": "not-open",
    "company": "AlphaSights",
    "name": "2027 Summer Internship"
  },
  {
    "id": "e7y2r44j5b",
    "status": "not-open",
    "company": "BCG",
    "name": "2027 Summer Associate"
  },
  {
    "id": "er5m2y0dsk",
    "status": "open",
    "company": "Morgan Stanley",
    "name": "2027 Summer Analyst Program"
  },
  {
    "id": "fatnkyy0ta",
    "status": "not-open",
    "company": "DBS Bank",
    "name": "2027 Internship Programme"
  },
  {
    "id": "fmm51clvb1",
    "status": "not-open",
    "company": "Qube RT",
    "name": "2027 Internship"
  },
  {
    "id": "fuxbrdnfm6",
    "status": "not-open",
    "company": "McKinsey & Company",
    "name": "Business Analyst Intern"
  },
  {
    "id": "hqomrjgg90",
    "status": "not-open",
    "company": "EY",
    "name": "[Programme Name TBC]"
  },
  {
    "id": "iemhue4al6",
    "status": "not-open",
    "company": "NCB",
    "name": "2027 Summer Internship Program"
  },
  {
    "id": "if2uyb9945",
    "status": "not-open",
    "company": "ExodusPoint",
    "name": "Fixed Income Internship"
  },
  {
    "id": "iiru386x3s",
    "status": "not-open",
    "company": "Blackstone",
    "name": "2027 Summer Analyst"
  },
  {
    "id": "jdv1hlp4r1",
    "status": "open",
    "company": "Bain & Company",
    "name": "Associate Consultant Internship"
  },
  {
    "id": "jjx8yjwtta",
    "status": "not-open",
    "company": "CBRE",
    "name": "Summer Internship 2027"
  },
  {
    "id": "jknmr6c9l3",
    "status": "not-open",
    "company": "IMC Trading",
    "name": "[Programme Name TBC]"
  },
  {
    "id": "jl85wm5qbq",
    "status": "not-open",
    "company": "Santander",
    "name": "[Programme Name TBC]"
  },
  {
    "id": "jraraofh1x",
    "status": "not-open",
    "company": "MUFG",
    "name": "Summer Internship Programme 2027"
  },
  {
    "id": "jti6vs75mv",
    "status": "not-open",
    "company": "Macquarie Group",
    "name": "2027 Summer Internship"
  },
  {
    "id": "k9kzhtt3xb",
    "status": "open",
    "company": "Hudson River Trading",
    "name": "Algorithm Developer (Quant Researcher) - 2027 Grads"
  },
  {
    "id": "ko12p6ee5f",
    "status": "not-open",
    "company": "The Walt Disney Company",
    "name": "2027 Summer Internship - Financial Management"
  },
  {
    "id": "kz8j731sr8",
    "status": "not-open",
    "company": "Synpulse",
    "name": "Internship 2027"
  },
  {
    "id": "l377k62hsa",
    "status": "not-open",
    "company": "Computershare",
    "name": "Internship, Financial Services"
  },
  {
    "id": "lg2uyus1wg",
    "status": "not-open",
    "company": "Standard Chartered",
    "name": "Internship Programme 2027"
  },
  {
    "id": "lkbqjutf8o",
    "status": "not-open",
    "company": "Polymer Capital",
    "name": "2027 Summer Intern"
  },
  {
    "id": "m3yn16ovnx",
    "status": "not-open",
    "company": "Moelis & Co",
    "name": "2027 Summer Analyst, Investment Banking"
  },
  {
    "id": "m684um3ozo",
    "status": "not-open",
    "company": "PwC",
    "name": "[Programme Name TBC]"
  },
  {
    "id": "mbth32ptbp",
    "status": "open",
    "company": "HSBC",
    "name": "2027 Summer Internship"
  },
  {
    "id": "mya89wytmj",
    "status": "not-open",
    "company": "PineBridge Investments",
    "name": "Intern - Client Relations"
  },
  {
    "id": "na1bi4msts",
    "status": "not-open",
    "company": "Jump Trading",
    "name": "Campus Quantitative Trader (Intern)"
  },
  {
    "id": "nb08dmc1fb",
    "status": "not-open",
    "company": "HKEX",
    "name": "2027 Summer Internship"
  },
  {
    "id": "ng5wom3608",
    "status": "not-open",
    "company": "Schroders",
    "name": "2027 Internship Programme"
  },
  {
    "id": "o1qlosyukj",
    "status": "not-open",
    "company": "Galaxy",
    "name": "2027 Summer Internship"
  },
  {
    "id": "omky7f3m96",
    "status": "open",
    "company": "Susquehanna International Group",
    "name": "Quantitative Trading/Research Internship: Summer 2027"
  },
  {
    "id": "otcncc9o5s",
    "status": "open",
    "company": "Barclays",
    "name": "Summer Internship Programme 2027"
  },
  {
    "id": "ozo5bgprpz",
    "status": "open",
    "company": "UBS",
    "name": "2027 Summer Internship"
  },
  {
    "id": "p8twuo81u3",
    "status": "not-open",
    "company": "HKEX",
    "name": "2027 Summer Internship Programme"
  },
  {
    "id": "pai5x002cn",
    "status": "open",
    "company": "DV Trading",
    "name": "2027 Summer Internship - Trading"
  },
  {
    "id": "pkfvwmens8",
    "status": "not-open",
    "company": "Tradeweb",
    "name": "2027 Summer Internship"
  },
  {
    "id": "pl1squugqk",
    "status": "not-open",
    "company": "Deutsche Bank",
    "name": "2027 Summer Internship Programme"
  },
  {
    "id": "puanwzkrm0",
    "status": "not-open",
    "company": "Flow Traders",
    "name": "Trading Intern"
  },
  {
    "id": "qis03upocq",
    "status": "not-open",
    "company": "Crédit Agricole",
    "name": "2027 Summer Internship"
  },
  {
    "id": "qqbhusct1g",
    "status": "closed",
    "company": "Bastion Trading",
    "name": "Internship for Trading & Quant Summer 2027"
  },
  {
    "id": "r2hrey23xt",
    "status": "not-open",
    "company": "BNY Mellon",
    "name": "[Programme Name TBC]"
  },
  {
    "id": "rd96dmlony",
    "status": "not-open",
    "company": "PJT Partners",
    "name": "2027 Summer Analyst"
  },
  {
    "id": "rv72ikyajm",
    "status": "not-open",
    "company": "Neuberger Berman",
    "name": "2027 Summer Intern"
  },
  {
    "id": "s0x7rwfbe2",
    "status": "open",
    "company": "Capula Investment Management",
    "name": "Trading and Research Summer Internship 2027"
  },
  {
    "id": "tx3gfh6gkh",
    "status": "open",
    "company": "Teneo",
    "name": "Internship, Financial Advisory"
  },
  {
    "id": "tym78pkt3z",
    "status": "not-open",
    "company": "CICC",
    "name": "2027 Summer Intern"
  },
  {
    "id": "uayvhzgxgy",
    "status": "not-open",
    "company": "WTW",
    "name": "Summer Intern - Investment"
  },
  {
    "id": "uo211d6sw8",
    "status": "not-open",
    "company": "Bank of China",
    "name": "2027 Gen Z Internship Programme"
  },
  {
    "id": "v02o5nax8v",
    "status": "not-open",
    "company": "Jane Street",
    "name": "Internship 2027"
  },
  {
    "id": "w4xlvzeuvn",
    "status": "not-open",
    "company": "Deloitte",
    "name": "2027 Summer Internship"
  },
  {
    "id": "wjx0rohy4n",
    "status": "open",
    "company": "BlackRock",
    "name": "2027 Summer Internship Program"
  },
  {
    "id": "x0tiwlpaeh",
    "status": "not-open",
    "company": "Wells Fargo",
    "name": "2027 Summer Analyst"
  },
  {
    "id": "x2hhrcnosb",
    "status": "not-open",
    "company": "AIA",
    "name": "2027 Summer Internship Programme"
  },
  {
    "id": "x5nbgl56ph",
    "status": "not-open",
    "company": "Mizuho",
    "name": "2027 Summer Internship program"
  },
  {
    "id": "xl1sojp8iv",
    "status": "not-open",
    "company": "PIMCO",
    "name": "2027 Summer Internship"
  },
  {
    "id": "xof18gf1uw",
    "status": "not-open",
    "company": "EFG International",
    "name": "Intern"
  },
  {
    "id": "xopq5to0i1",
    "status": "not-open",
    "company": "Third Bridge",
    "name": "2027 Summer Intern"
  },
  {
    "id": "ycyfbtrmuf",
    "status": "open",
    "company": "Balyasny Asset Management",
    "name": "Quantitative Researcher (Summer Internship)"
  },
  {
    "id": "yjdbuwh56d",
    "status": "open",
    "company": "Citi",
    "name": "Summer Analyst, 2027"
  },
  {
    "id": "ykhz7gp378",
    "status": "not-open",
    "company": "Y-Intercept",
    "name": "Quantitative Researcher Intern"
  },
  {
    "id": "yxa1agz0n9",
    "status": "not-open",
    "company": "Verition Fund Management",
    "name": "2027 Summer Internship"
  },
  {
    "id": "zjl6hjnzdm",
    "status": "not-open",
    "company": "KPMG",
    "name": "[Programme Name TBC]"
  },
  {
    "id": "zjv6wfqco3",
    "status": "not-open",
    "company": "Rothschild & Co.",
    "name": "2027 Summer Internship Programme"
  }
]
